rotate_keyboard_layout.py
setup.py
rotate_keyboard_layout.egg-info/PKG-INFO
rotate_keyboard_layout.egg-info/SOURCES.txt
rotate_keyboard_layout.egg-info/dependency_links.txt
rotate_keyboard_layout.egg-info/entry_points.txt
rotate_keyboard_layout.egg-info/top_level.txt