Metadata-Version: 1.1
Name: rotate-keyboard-layout
Version: 1.0.1
Summary: Simple script to rotate among X keyboard layouts
Home-page: https://github.com/thusoy/rotate-keyboard-layout
Author: Tarjei Husøy
Author-email: git@thusoy.com
License: UNKNOWN
Platform: UNKNOWN
Classifier: Development Status :: 4 - Beta
Classifier: Intended Audience :: End Users/Desktop
Classifier: Environment :: Console
Classifier: Environment :: X11 Applications
Classifier: License :: OSI Approved :: MIT License
Classifier: Programming Language :: Python :: 2.6
Classifier: Programming Language :: Python :: 2.7
Classifier: Programming Language :: Python :: 3.3
Classifier: Programming Language :: Python :: 3.4
Classifier: Programming Language :: Python :: 3.5
Classifier: Programming Language :: Python :: 3.6
Classifier: Topic :: Desktop Environment
Classifier: Topic :: Utilities
